{ "001": "गेहूँ",
  "002": "धान",
  "003": "चावल",
  "004": "मक्का",
  "005": "ज्वार",
  "006": "चना",
  "007": "अरहर / तुअर",
  "008": "उड़द",
  "009": "मूंग",
  "010": "मूंगफली",
  "011": "तिल (तिल्ली)",
  "012": "सरसों",
  "013": "सोयाबीन",
  "014": "सूरजमुखी",
  "015": "कपास",
  "016": "जूट",
  "017": "सेब",
  "018": "संतरा",
  "019": "केला",
  "020": "आम",
  "021": "अनानास",
  "022": "अंगूर",
  "023": "प्याज",
  "024": "आलू",
  "025": "लहसुन",
  "026": "लाल मिर्च",
  "027": "सूखी अदरक",
  "028": "बाजरा",
  "029": "जौ",
  "030": "रागी",
  "034": "फूल गोभी",
  "035": "बैंगन",
  "036": "काजू",
  "038": "काली मिर्च",
  "039": "हल्दी",
  "040": "इलायची",
  "041": "सुपारी",
  "042": "जीरा",
  "043": "धनिया के पत्ते",
  "044": "चाय",
  "045": "कॉफी",
  "046": "मैथी के पत्ते",
  "047": "मैथी (मैथीदाना)",
  "048": "चीनी",
  "049": "अरहर",
  "050": "हरा मटर",
  "051": "बिनौला",
  "059": "कुसुम",
  "060": "मुहब्बत",
  "061": "खरीफ माश",
  "062": "रिकबकन",
  "063": "मसूर",
  "064": "खेत मटर",
  "065": "राया",
  "066": "टोरिया",
  "067": "अलसी",
  "069": "धैनचा",
  "071": "चीकू (सपोटा)",
  "072": "पपीता",
  "073": "तरबूज",
  "074": "गुड़",
  "075": "ग्वार",
  "076": "तारामिरा",
  "077": "मौसंबी (मीठा नींबू)",
  "078": "टमाटर",
  "080": "ग्वार फली",
  "081": "करेला",
  "082": "लौकी",
  "083": "सफेद पेठा",
  "084": "कद्दू",
  "085": "भिंडी",
  "086": "चौलाई",
  "087": "हरी मिर्च",
  "088": "शिमला मिर्च",
  "089": "लोबिया (सब्जी)",
  "090": "हरा केला",
  "091": "दाल (अवारे)",
  "092": "लोबिया (लोबिया/करमानी)",
  "093": "मटाकी",
  "094": "फलियाँ",
  "095": "मोठ दाल",
  "096": "लाक (तेवड़ा)",
  "097": "अन्य दालें",
  "098": "रामतिल",
  "099": "कपास के बीज",
  "100": "साबूदाना",
  "102": "जिमीकंद",
  "103": "अदरक (हरा)",
  "104": "कोको",
  "105": "लौंग",
  "106": "जायफल",
  "107": "जावित्री",
  "108": "धनिया",
  "109": "काली मिर्च (Garbled)",
  "110": "काली मिर्च (Ungarbled)",
  "111": "रबड़",
  "112": "नारियल के बीज",
  "113": "बड़ा चना",
  "114": "कुलथी",
  "115": "करमानी",
  "116": "थिनाई (इतालवी बाजरा)",
  "117": "कोदो बाजरा (वरगु)",
  "119": "हाइब्रिड कुम्बू",
  "120": "टी.वी. कुम्बू",
  "121": "फॉक्सटेल बाजरा (नवाने)",
  "122": "समान / सावी",
  "123": "अरंडी के बीज",
  "124": "होंगे बीज",
  "125": "हिप्पे बीज",
  "126": "नीम के बीज",
  "128": "पुंडी बीज",
  "129": "खोपरा",
  "130": "अंबाडा बीज",
  "132": "सूखी मिर्च",
  "135": "सोअनफ़",
  "137": "अजवान",
  "138": "नारियल",
  "139": "सनहेम्प",
  "140": "सुपारी",
  "141": "तंबाकू",
  "142": "हरड़",
  "143": "सुपारी के पत्ते",
  "150": "गन्ना",
  "151": "गुड़",
  "152": "शकरकंद",
  "153": "गाजर",
  "154": "पत्ता गोभी",
  "155": "भिंडी",
  "156": "सर्पगुर्द (स्नेकगार्ड)",
  "157": "चुकंदर",
  "158": "सफेद कद्दू",
  "159": "खीरा",
  "160": "तोरी (रिज गार्ड)",
  "161": "मूली",
  "162": "थोंडेकाई",
  "163": "डस्टर बीन्स",
  "164": "शिमला मिर्च",
  "165": "ग्रीन अवारे (साबुत)",
  "166": "अलसंदिकाई",
  "167": "चाउ चाउ",
  "168": "सहजन (मोरिंगा)",
  "169": "चप्पाराड अवारे",
  "170": "थोग्रिकाई",
  "171": "पत्तेदार सब्जी",
  "172": "आम (कच्चा-पका हुआ)",
  "173": "मीठा कद्दू",
  "174": "गीली मटर",
  "175": "जमामखान",
  "176": "सीमाबदनेकाई",
  "177": "नूल खोल",
  "178": "सुवर्णा गद्दे",
  "180": "नींबू",
  "181": "मारासेबू",
  "182": "कटहल",
  "183": "सिद्दोता",
  "184": "जामुन (नराले हन्नू)",
  "185": "अमरूद",
  "187": "खरबूजा (करबुजा)",
  "188": "चकोथा",
  "189": "बोरेहन्नू",
  "190": "अनार",
  "200": "कच्चा नारियल",
  "201": "सीतापाल",
  "203": "लकड़ी",
  "204": "बांस",
  "205": "बेंत",
  "206": "लकड़ी (इंधन के लिए लकड़ी)",
  "207": "सोपनट (अंटावाला / रैठा)",
  "208": "इमली के बीज",
  "209": "अंतावाला",
  "210": "जूट के बीज",
  "212": "गाय",
  "213": "बैल",
  "214": "साँड़",
  "215": "बछड़ा",
  "216": "नर भैंस",
  "217": "मादा भैंस",
  "218": "भेड़",
  "219": "बकरी",
  "220": "सुअर",
  "221": "अंजीर",
  "222": "नियारले हन्नू",
  "223": "नेल्ली काई",
  "224": "बंच बीन्स",
  "225": "मरागेंसु",
  "226": "त्वचा और छाला",
  "228": "गुलाब (ढीला)",
  "229": "चमेली",
  "230": "काकाडा",
  "231": "गुलदाउदी (ढीला)",
  "232": "एस्टर",
  "233": "कंकम्बरा",
  "234": "ट्यूब फूल",
  "235": "गेंदा (कलकत्ता)",
  "236": "शहद",
  "237": "बाजरा",
  "238": "काजू की गिरी",
  "240": "पोलहर्ब",
  "241": "चेन्नांगी (साबुत)",
  "242": "सुरम",
  "243": "कुचुर",
  "244": "रतालू",
  "245": "नरगासी",
  "246": "सोम्पू",
  "247": "सरसुम",
  "248": "राजगीर",
  "249": "घी",
  "250": "जावी",
  "252": "हरालेकाई",
  "253": "सीगू",
  "254": "पुंडी",
  "255": "सुवा (डिल बीज)",
  "256": "ईसबगुल (साइलियम)",
  "258": "मोआथ दाल",
  "259": "मसूर दाल",
  "260": "अरहर दाल",
  "261": "इमली फल",
  "262": "पीटा हुआ चावल",
  "263": "बंगाल ग्राम दाल (चना दाल)",
  "264": "काली चना दाल (उड़द दाल)",
  "265": "हरी चना दाल (मूंग दाल)",
  "266": "नारियल तेल",
  "267": "मूंगफली का तेल",
  "268": "मूंगफली के बीज",
  "269": "अवारे दाल",
  "270": "अरंडी का तेल",
  "271": "सज्जे",
  "272": "मक्खन",
  "273": "डालडा",
  "274": "बालेकाई",
  "276": "तिल का तेल",
  "277": "मौसमी पत्ते",
  "278": "सूखे अंगूर",
  "279": "गुरेल्लु",
  "280": "एक प्रकार का वृक्ष",
  "281": "अलासांडे ग्राम",
  "282": "टक्कर मारना",
  "283": "मादा बकरी",
  "284": "बुल्लर",
  "285": "सूरजमुखी के बीज",
  "286": "सोजी",
  "287": "गेहूं का आटा",
  "288": "मैदा आटा",
  "290": "चोकर",
  "291": "साबू दान",
  "293": "टूटा चावल",
  "294": "बेसन",
  "295": "चेन्नांगी दाल",
  "296": "हाथी रतालू (सूरन)",
  "297": "रतालू",
  "298": "फ्रेंच बीन्स (फ्रासबीन)",
  "299": "भारतीय बीन्स (सीम)",
  "300": "सूरत बीन्स (पापड़ी)",
  "301": "कबूतर मटर (अरहर फली)",
  "302": "छोटी लौकी (कुंदरू)",
  "303": "परवल",
  "304": "लंबा तरबूज (ककरी)",
  "305": "करताली (कंटोला)",
  "306": "गोल लौकी",
  "307": "चूहे की पूंछ वाली मूली (मोगरी)",
  "308": "मटर कॉड",
  "309": "हल्दी (कच्ची)",
  "310": "नींबू",
  "311": "स्पंज लौकी",
  "312": "मूंगफली की फली (कच्ची)",
  "313": "पपीता (कच्चा)",
  "314": "मूंगफली (टूटी हुई)",
  "315": "कोका",
  "316": "दालचीनी",
  "317": "कचोलम",
  "318": "कोलाकेसिया",
  "320": "झाड़ू (फूल झाड़ू)",
  "321": "तेजपत्ता",
  "322": "रालवुड",
  "323": "टॉर्चवुड",
  "324": "सरसों का तेल",
  "325": "बादाम",
  "326": "खुबानी (जर्दालु / खुमानी)",
  "327": "पर्सिमोन (जापानी फल)",
  "328": "चेरी",
  "329": "आलूबुखारा",
  "330": "नाशपाती (मारसेबू)",
  "331": "आड़ू",
  "332": "स्क्वैश (चप्पल कद्दू)",
  "335": "महुआ",
  "336": "किन्नू",
  "337": "लुकाड",
  "338": "केसर",
  "339": "कमल की छड़ें",
  "340": "मशरूम",
  "341": "शलजम",
  "342": "पालक",
  "343": "अखरोट",
  "344": "भारतीय कोल्ज़ा (सरसों)",
  "345": "सूखा चारा",
  "346": "हरा चारा",
  "347": "मटर (सूखी)",
  "348": "ऊन",
  "349": "टिंडा",
  "350": "गलगल (नींबू)",
  "351": "लीची",
  "352": "कस्टर्ड एप्पल (शरीफा)",
  "353": "बकरी के बाल",
  "354": "ऊंट के बाल",
  "355": "आंवला (नेल्ली काई)",
  "357": "बेर (ज़िज़िफ़स / बोरेहन्नू)",
  "358": "हरा प्याज",
  "359": "कच्चा चना (छोलिया)",
  "360": "पुदीना",
  "361": "मिस्री तिपतिया घास (बरसीम)",
  "362": "काबुली चना (सफेद छोले)",
  "363": "ग्लेडियोलस कटे फूल",
  "364": "ग्लेडियोलस बल्ब",
  "365": "फूल झाड़ू",
  "366": "मछली",
  "367": "अंडा",
  "368": "मुर्गा",
  "369": "मुर्गी",
  "370": "बत्तख",
  "371": "महुआ बीज (हिप्पे बीज)",
  "372": "खोया",
  "373": "रोज़ (टाटा)",
  "374": "रोज़ (स्थानीय)",
  "375": "कारनेशन",
  "376": "जरबारा",
  "377": "ट्यूब रोज़ (एकल)",
  "378": "लिली",
  "379": "एंथोरियम",
  "380": "बॉप",
  "381": "आर्किड",
  "382": "दैला (चांदनी)",
  "401": "ट्यूब रोज़ (डबल)",
  "402": "गुलदाउदी",
  "403": "कमल",
  "404": "पट्टी कलकत्ता",
  "405": "गेंदा (ढीला)",
  "406": "जाफरी",
  "407": "मार्गरेट",
  "408": "ट्यूब रोज़ (ढीला)",
  "409": "रायबेल",
  "410": "डेल्हा",
  "411": "महेदी",
  "412": "सफेद मटर",
  "413": "ग्वार बीज (क्लस्टर बीन्स बीज)",
  "414": "धान (बासमती)",
  "415": "कुटकी",
  "416": "बटर्री (संगत)",
  "417": "अम्बाडी / मेस्ता",
  "418": "बेल",
  "419": "अमरनाथ (लाल)",
  "420": "अन्य हरी और ताजी सब्ज़ियाँ",
  "421": "अफीम के बीज",
  "422": "आम पाउडर",
  "423": "सूखा हुआ आम",
  "424": "कलौंजी",
  "425": "अफीम के डंठल",
  "426": "कुटकी",
  "427": "मकॉय",
  "428": "मूलेटी",
  "429": "सफेद म्यूसली",
  "430": "पत्थर की चक्की",
  "431": "पिप्पली",
  "432": "तिक्त हल्दी",
  "433": "सनय",
  "434": "शतावरी",
  "435": "तुलसी",
  "436": "वदंग",
  "437": "वत्सनाभ",
  "438": "चंद्रशूर",
  "439": "करंज के बीज",
  "440": "स्टीविया",
  "441": "पलाश के फूल",
  "442": "धवाई के फूल",
  "443": "अश्वगंधा",
  "444": "असालिया",
  "445": "कलौंजी",
  "446": "म्यूसली",
  "447": "पुपाड़िया",
  "448": "भूमि आमलिया",
  "449": "ब्राह्मी",
  "450": "चंदन",
  "451": "अबसिंथ",
  "452": "गुड़ूची",
  "453": "गुड़मार",
  "454": "गुग्गल",
  "455": "जटामांसी",
  "456": "कलीहारी",
  "457": "कालमेघ",
  "458": "कोकम",
  "459": "कूठ",
  "460": "रतनजोत",
  "461": "गुली",
  "462": "ग्लेडियेरिया",
  "463": "ट्यूलिप",
  "464": "सेवांती",
  "465": "आयरिश",
  "466": "स्वीट सुल्तान",
  "467": "सिनेरेरिया",
  "468": "साल्विया",
  "469": "गिप्सोफिला",
  "470": "लिमोनिया (स्थिति)",
  "471": "गॉम्फरेना",
  "472": "कॉस्सांद्रा",
  "473": "हाइड्रेंजिया",
  "474": "हेलिकोनिया प्रजातियाँ",
  "475": "गोल्डन रोड",
  "476": "डायन्थस",
  "477": "स्वीट विलियम",
  "478": "क्लार्किया",
  "479": "ल्यूपिन",
  "480": "कैलेंडुला",
  "481": "केवड़ा",
  "482": "बलसम",
  "483": "केला का फूल",
  "484": "केले का तना",
  "485": "केले का पत्ता",
  "486": "करी पत्ता",
  "487": "ब्रोकोली",
  "488": "सुन्दैकाई",
  "489": "पेरंदाई",
  "490": "सिरु किझागु",
  "491": "बज्जी मिर्च",
  "492": "डबल बीन्स",
  "493": "लाल पत्ता गोभी",
  "494": "आंवला (नेल्लीकाई)",
  "495": "ड्रैगन फ्रूट",
  "496": "जामुन",
  "497": "ब्रेड फ्रूट",
  "498": "जंगली नींबू",
  "499": "किलौड़ी",
  "500": "नेरियम",
  "501": "काकतन",
  "502": "मरिकोजुन्थु",
  "503": "तुलसी",
  "504": "म. इंजी",
  "505": "अशगंध",
  "506": "अशोक",
  "507": "अतीस",
  "508": "बेहड़ा",
  "509": "चिरोंजी",
  "510": "अलसी के बीज",
  "511": "गोंद",
  "512": "हरड़ा",
  "513": "जैई",
  "514": "खिर्नी",
  "515": "लाहा",
  "516": "खरबूजे के बीज",
  "517": "राला",
  "518": "रामफल",
  "519": "रायी",
  "520": "सोहा",
  "521": "सिंघाड़ा",
  "522": "मोम"

}





